setup.py
Flask_Principal.egg-info/PKG-INFO
Flask_Principal.egg-info/SOURCES.txt
Flask_Principal.egg-info/dependency_links.txt
Flask_Principal.egg-info/not-zip-safe
Flask_Principal.egg-info/requires.txt
Flask_Principal.egg-info/top_level.txt
flask_principal/__init__.py
flask_principal/backport.py