Metadata-Version: 1.0
Name: Flask-Principal
Version: 0.3
Summary: Identity management for flask
Home-page: http://packages.python.org/Flask-Principal/
Author: Matt Wright
Author-email: matt@nobien.net
License: MIT
Platform: any
Classifier: Development Status :: 4 - Beta
Classifier: Environment :: Web Environment
Classifier: Intended Audience :: Developers
Classifier: License :: OSI Approved :: MIT License
Classifier: Operating System :: OS Independent
Classifier: Programming Language :: Python
Classifier: Topic :: Internet :: WWW/HTTP :: Dynamic Content
Classifier: Topic :: Software Development :: Libraries :: Python Modules
